{
"meta":{"test_sets":["test"],"test_metrics":[{"best_value":"Min","name":"RMSE"}],"learn_metrics":[{"best_value":"Min","name":"RMSE"}],"launch_mode":"Train","parameters":"","iteration_count":1000,"learn_sets":["learn"],"name":"experiment"},
"iterations":[
{"learn":[108.4426562],"iteration":0,"passed_time":0.02093624978,"remaining_time":20.91531353,"test":[94.93031931]},
{"learn":[107.9330591],"iteration":1,"passed_time":0.04072407479,"remaining_time":20.32131332,"test":[94.58301663]},
{"learn":[107.2620253],"iteration":2,"passed_time":0.07439947209,"remaining_time":24.72542456,"test":[93.96778087]},
{"learn":[106.5698796],"iteration":3,"passed_time":0.1052849293,"remaining_time":26.2159474,"test":[93.56333288]},
{"learn":[105.8690142],"iteration":4,"passed_time":0.137252091,"remaining_time":27.3131661,"test":[93.06193595]},
{"learn":[105.1649842],"iteration":5,"passed_time":0.1670185264,"remaining_time":27.66940254,"test":[92.86267449]},
{"learn":[104.1608422],"iteration":6,"passed_time":0.1976709213,"remaining_time":28.04103212,"test":[92.5555997]},
{"learn":[103.6290389],"iteration":7,"passed_time":0.2278111133,"remaining_time":28.24857804,"test":[92.16919441]},
{"learn":[103.3276596],"iteration":8,"passed_time":0.2366127268,"remaining_time":26.05369025,"test":[91.80594131]},
{"learn":[103.0036749],"iteration":9,"passed_time":0.2463565741,"remaining_time":24.38930084,"test":[91.50564781]},
{"learn":[102.4727493],"iteration":10,"passed_time":0.2748888244,"remaining_time":24.7150043,"test":[91.24485434]},
{"learn":[101.9030152],"iteration":11,"passed_time":0.3062718476,"remaining_time":25.21638212,"test":[91.03552908]},
{"learn":[101.3087997],"iteration":12,"passed_time":0.3367973866,"remaining_time":25.57069389,"test":[90.83718878]},
{"learn":[101.039909],"iteration":13,"passed_time":0.3451183105,"remaining_time":24.30618958,"test":[90.60912799]},
{"learn":[100.6491521],"iteration":14,"passed_time":0.3727688573,"remaining_time":24.4784883,"test":[90.40815783]},
{"learn":[100.1248879],"iteration":15,"passed_time":0.4045711066,"remaining_time":24.88112306,"test":[90.17622175]},
{"learn":[99.65329067],"iteration":16,"passed_time":0.4358835934,"remaining_time":25.20432778,"test":[89.90214451]},
{"learn":[99.1612729],"iteration":17,"passed_time":0.4681300347,"remaining_time":25.53909411,"test":[89.8613329]},
{"learn":[98.81204327],"iteration":18,"passed_time":0.5004530171,"remaining_time":25.83917946,"test":[89.66439844]},
{"learn":[98.26921105],"iteration":19,"passed_time":0.5360961063,"remaining_time":26.26870921,"test":[89.49673654]},
{"learn":[97.92522254],"iteration":20,"passed_time":0.5671702535,"remaining_time":26.44093706,"test":[89.49802949]},
{"learn":[97.44800746],"iteration":21,"passed_time":0.5971607456,"remaining_time":26.54650951,"test":[89.32066331]},
{"learn":[96.76320228],"iteration":22,"passed_time":0.6278310285,"remaining_time":26.66917021,"test":[89.13202125]},
{"learn":[96.45035436],"iteration":23,"passed_time":0.6591644792,"remaining_time":26.80602215,"test":[89.05774857]},
{"learn":[96.04230637],"iteration":24,"passed_time":0.6908284545,"remaining_time":26.94230972,"test":[88.88790178]},
{"learn":[95.59624492],"iteration":25,"passed_time":0.7260014842,"remaining_time":27.19713252,"test":[88.88342981]},
{"learn":[95.22939267],"iteration":26,"passed_time":0.7586660964,"remaining_time":27.34007822,"test":[88.88506861]},
{"learn":[94.89372582],"iteration":27,"passed_time":0.7907565709,"remaining_time":27.45054953,"test":[88.85847936]},
{"learn":[94.41756948],"iteration":28,"passed_time":0.8225550719,"remaining_time":27.54141293,"test":[88.98951231]},
{"learn":[94.16760324],"iteration":29,"passed_time":0.8555312019,"remaining_time":27.66217553,"test":[88.84526722]},
{"learn":[93.96402169],"iteration":30,"passed_time":0.8879700958,"remaining_time":27.75622654,"test":[88.81805116]},
{"learn":[93.76060279],"iteration":31,"passed_time":0.9201564799,"remaining_time":27.83473352,"test":[88.77190789]},
{"learn":[93.448617],"iteration":32,"passed_time":0.9555503027,"remaining_time":28.00051948,"test":[88.73827993]},
{"learn":[93.05174599],"iteration":33,"passed_time":0.987505802,"remaining_time":28.05678249,"test":[88.87920522]},
{"learn":[92.77041857],"iteration":34,"passed_time":1.01844823,"remaining_time":28.08007263,"test":[88.90657831]},
{"learn":[92.42232291],"iteration":35,"passed_time":1.048965515,"remaining_time":28.08896545,"test":[88.98986267]},
{"learn":[92.18071157],"iteration":36,"passed_time":1.081461576,"remaining_time":28.14722967,"test":[88.88900394]},
{"learn":[91.93698904],"iteration":37,"passed_time":1.113401522,"remaining_time":28.18663853,"test":[88.86337001]},
{"learn":[91.69843045],"iteration":38,"passed_time":1.143382581,"remaining_time":28.17411949,"test":[88.86120102]},
{"learn":[91.57878504],"iteration":39,"passed_time":1.174461723,"remaining_time":28.18708134,"test":[88.7675558]},
{"learn":[91.33735373],"iteration":40,"passed_time":1.206095406,"remaining_time":28.21086571,"test":[88.72635486]},
{"learn":[91.31711272],"iteration":41,"passed_time":1.217795592,"remaining_time":27.77733755,"test":[88.73829774]},
{"learn":[91.06437468],"iteration":42,"passed_time":1.248740135,"remaining_time":27.79172812,"test":[88.68141813]},
{"learn":[90.76671273],"iteration":43,"passed_time":1.279624863,"remaining_time":27.80275838,"test":[88.78570647]},
{"learn":[90.35960784],"iteration":44,"passed_time":1.309690334,"remaining_time":27.79453931,"test":[88.71530569]},
{"learn":[89.96595295],"iteration":45,"passed_time":1.341089461,"remaining_time":27.81302926,"test":[88.6372562]},
{"learn":[89.58888917],"iteration":46,"passed_time":1.373066176,"remaining_time":27.84110778,"test":[88.73043595]},
{"learn":[89.23798905],"iteration":47,"passed_time":1.408710584,"remaining_time":27.93942658,"test":[88.75158598]},
{"learn":[88.96804087],"iteration":48,"passed_time":1.442253553,"remaining_time":27.99149242,"test":[88.81666324]},
{"learn":[88.74336061],"iteration":49,"passed_time":1.473197074,"remaining_time":27.9907444,"test":[88.88138472]},
{"learn":[88.56754157],"iteration":50,"passed_time":1.504447857,"remaining_time":27.99452972,"test":[88.83950966]},
{"learn":[88.26209799],"iteration":51,"passed_time":1.53611514,"remaining_time":28.00456063,"test":[88.83559894]},
{"learn":[88.18025391],"iteration":52,"passed_time":1.567058209,"remaining_time":28.00007781,"test":[88.84536284]},
{"learn":[88.02859214],"iteration":53,"passed_time":1.598396073,"remaining_time":28.0015312,"test":[88.72148367]},
{"learn":[87.7397807],"iteration":54,"passed_time":1.630882414,"remaining_time":28.02152511,"test":[88.69995931]},
{"learn":[87.50657026],"iteration":55,"passed_time":1.663376767,"remaining_time":28.03977978,"test":[88.7421226]},
{"learn":[87.35927125],"iteration":56,"passed_time":1.694842059,"remaining_time":28.03922916,"test":[88.72783658]},
{"learn":[87.1823427],"iteration":57,"passed_time":1.726269339,"remaining_time":28.03699513,"test":[88.61679593]},
{"learn":[86.87284148],"iteration":58,"passed_time":1.758017219,"remaining_time":28.0388848,"test":[88.61754482]},
{"learn":[86.63962776],"iteration":59,"passed_time":1.789136553,"remaining_time":28.029806,"test":[88.63395082]},
{"learn":[86.60822693],"iteration":60,"passed_time":1.82157312,"remaining_time":28.04028131,"test":[88.63898756]},
{"learn":[86.45296585],"iteration":61,"passed_time":1.855736197,"remaining_time":28.07549278,"test":[88.68363065]},
{"learn":[86.03839598],"iteration":62,"passed_time":1.892198685,"remaining_time":28.14270107,"test":[88.74459421]},
{"learn":[85.84881735],"iteration":63,"passed_time":1.923136753,"remaining_time":28.12587501,"test":[88.84164923]},
{"learn":[85.56918284],"iteration":64,"passed_time":1.953808145,"remaining_time":28.10477871,"test":[88.75337515]},
{"learn":[85.33742802],"iteration":65,"passed_time":1.985827946,"remaining_time":28.10247427,"test":[88.69220652]},
{"learn":[85.23966013],"iteration":66,"passed_time":2.017726876,"remaining_time":28.09759963,"test":[88.66745031]},
{"learn":[85.04734076],"iteration":67,"passed_time":2.049580025,"remaining_time":28.09130269,"test":[88.68051054]},
{"learn":[84.99165282],"iteration":68,"passed_time":2.081790797,"remaining_time":28.08909032,"test":[88.68785601]},
{"learn":[84.60245589],"iteration":69,"passed_time":2.113728786,"remaining_time":28.08239673,"test":[88.62924224]},
{"learn":[84.39986326],"iteration":70,"passed_time":2.145166243,"remaining_time":28.06844281,"test":[88.74975043]},
{"learn":[84.33360553],"iteration":71,"passed_time":2.177275421,"remaining_time":28.06266099,"test":[88.75907842]},
{"learn":[84.06178876],"iteration":72,"passed_time":2.209034144,"remaining_time":28.05170756,"test":[88.69459336]},
{"learn":[84.04502333],"iteration":73,"passed_time":2.236144017,"remaining_time":27.98201838,"test":[88.73082934]},
{"learn":[83.80010645],"iteration":74,"passed_time":2.268687927,"remaining_time":27.98048443,"test":[88.56847707]},
{"learn":[83.5987922],"iteration":75,"passed_time":2.303209664,"remaining_time":28.00218065,"test":[88.49769644]},
{"learn":[83.53352281],"iteration":76,"passed_time":2.338505514,"remaining_time":28.03169597,"test":[88.4920206]},
{"learn":[83.35991457],"iteration":77,"passed_time":2.368823741,"remaining_time":28.00071139,"test":[88.4766997]},
{"learn":[83.24602673],"iteration":78,"passed_time":2.399994851,"remaining_time":27.97968681,"test":[88.60528927]},
{"learn":[82.96456007],"iteration":79,"passed_time":2.431360415,"remaining_time":27.96064477,"test":[88.73984229]},
{"learn":[82.69666528],"iteration":80,"passed_time":2.462915796,"remaining_time":27.94345205,"test":[88.7330362]},
{"learn":[82.52066847],"iteration":81,"passed_time":2.495117267,"remaining_time":27.93314208,"test":[88.83163801]},
{"learn":[82.35642608],"iteration":82,"passed_time":2.527166222,"remaining_time":27.92061959,"test":[88.8820766]},
{"learn":[82.10548779],"iteration":83,"passed_time":2.559175015,"remaining_time":27.90719421,"test":[88.8813223]},
{"learn":[81.96478845],"iteration":84,"passed_time":2.591630468,"remaining_time":27.89813975,"test":[88.79354003]},
{"learn":[81.77849849],"iteration":85,"passed_time":2.622359111,"remaining_time":27.87018869,"test":[88.89779474]},
{"learn":[81.65116324],"iteration":86,"passed_time":2.654916549,"remaining_time":27.86136562,"test":[88.94083652]},
{"learn":[81.48878141],"iteration":87,"passed_time":2.686326362,"remaining_time":27.84010957,"test":[88.95337258]},
{"learn":[81.34933902],"iteration":88,"passed_time":2.71700194,"remaining_time":27.81110975,"test":[88.98676024]},
{"learn":[81.29936437],"iteration":89,"passed_time":2.740434278,"remaining_time":27.70883547,"test":[88.99901435]},
{"learn":[81.00378845],"iteration":90,"passed_time":2.774965378,"remaining_time":27.71915965,"test":[89.01596364]},
{"learn":[80.93303045],"iteration":91,"passed_time":2.809192424,"remaining_time":27.72550784,"test":[88.95276996]},
{"learn":[80.77332823],"iteration":92,"passed_time":2.841747671,"remaining_time":27.7146789,"test":[88.86649175]},
{"learn":[80.66305813],"iteration":93,"passed_time":2.874125248,"remaining_time":27.70167526,"test":[88.77075276]},
{"learn":[80.51066692],"iteration":94,"passed_time":2.905330624,"remaining_time":27.677097,"test":[88.7823332]},
{"learn":[80.37299949],"iteration":95,"passed_time":2.937642261,"remaining_time":27.66279795,"test":[88.76642942]},
{"learn":[80.34603801],"iteration":96,"passed_time":2.968573572,"remaining_time":27.63527768,"test":[88.71071182]},
{"learn":[80.34278116],"iteration":97,"passed_time":2.982630611,"remaining_time":27.45237562,"test":[88.71324157]},
{"learn":[80.16479232],"iteration":98,"passed_time":3.012099235,"remaining_time":27.41314557,"test":[88.72715104]},
{"learn":[80.07315513],"iteration":99,"passed_time":3.042985576,"remaining_time":27.38687018,"test":[88.74402646]},
{"learn":[80.00779436],"iteration":100,"passed_time":3.075186345,"remaining_time":27.37220321,"test":[88.77832906]},
{"learn":[79.87675298],"iteration":101,"passed_time":3.107547546,"remaining_time":27.35860487,"test":[88.83570488]},
{"learn":[79.54280969],"iteration":102,"passed_time":3.139310994,"remaining_time":27.33943652,"test":[88.92283158]},
{"learn":[79.53430543],"iteration":103,"passed_time":3.171739109,"remaining_time":27.32575232,"test":[88.91948949]},
{"learn":[79.39138113],"iteration":104,"passed_time":3.207366608,"remaining_time":27.33898204,"test":[88.87296227]},
{"learn":[79.28903253],"iteration":105,"passed_time":3.24206108,"remaining_time":27.34342081,"test":[88.8830268]},
{"learn":[79.21499681],"iteration":106,"passed_time":3.274741279,"remaining_time":27.33031741,"test":[88.89241973]},
{"learn":[79.04335149],"iteration":107,"passed_time":3.306485953,"remaining_time":27.30912472,"test":[88.90228981]},
{"learn":[78.96340008],"iteration":108,"passed_time":3.337978084,"remaining_time":27.28567407,"test":[88.92905372]},
{"learn":[78.91024005],"iteration":109,"passed_time":3.369244895,"remaining_time":27.26025415,"test":[88.91481409]},
{"learn":[78.69240726],"iteration":110,"passed_time":3.399959808,"remaining_time":27.23030873,"test":[88.89176863]},
{"learn":[78.44706117],"iteration":111,"passed_time":3.430088295,"remaining_time":27.19570005,"test":[88.98170242]},
{"learn":[78.36728377],"iteration":112,"passed_time":3.460712789,"remaining_time":27.1650641,"test":[88.97654085]},
{"learn":[78.31376077],"iteration":113,"passed_time":3.492300293,"remaining_time":27.14191281,"test":[88.94749763]},
{"learn":[78.18996774],"iteration":114,"passed_time":3.523516679,"remaining_time":27.11575879,"test":[88.94812729]},
{"learn":[78.10553541],"iteration":115,"passed_time":3.555365622,"remaining_time":27.09433802,"test":[88.99723888]},
{"learn":[77.94869603],"iteration":116,"passed_time":3.586121898,"remaining_time":27.06449261,"test":[88.9563622]},
{"learn":[77.73879079],"iteration":117,"passed_time":3.6176313,"remaining_time":27.04026107,"test":[88.94508014]},
{"learn":[77.49423927],"iteration":118,"passed_time":3.65330333,"remaining_time":27.04672465,"test":[88.98185137]},
{"learn":[77.30202877],"iteration":119,"passed_time":3.687583777,"remaining_time":27.04228103,"test":[88.95148826]},
{"learn":[77.16269479],"iteration":120,"passed_time":3.719071236,"remaining_time":27.01705468,"test":[89.00215766]},
{"learn":[77.04150101],"iteration":121,"passed_time":3.750352017,"remaining_time":26.99023828,"test":[88.95057126]},
{"learn":[76.9489108],"iteration":122,"passed_time":3.78277019,"remaining_time":26.971459,"test":[88.92765241]},
{"learn":[76.91585143],"iteration":123,"passed_time":3.814854494,"remaining_time":26.9501011,"test":[88.92832903]},
{"learn":[76.72234349],"iteration":124,"passed_time":3.845796716,"remaining_time":26.92057701,"test":[88.92966786]},
{"learn":[76.60834252],"iteration":125,"passed_time":3.877060604,"remaining_time":26.89326165,"test":[89.07536429]},
{"learn":[76.52153704],"iteration":126,"passed_time":3.910011236,"remaining_time":26.87747881,"test":[89.10940557]},
{"learn":[76.34776699],"iteration":127,"passed_time":3.941526143,"remaining_time":26.85164685,"test":[89.05734683]}
]}